blockbuster/__init__.py
blockbuster/blockbuster.py
blockbuster/py.typed
blockbuster-1.5.23.dist-info/METADATA
blockbuster-1.5.23.dist-info/WHEEL
blockbuster-1.5.23.dist-info/licenses/LICENSE
blockbuster-1.5.23.dist-info/RECORD
