Metadata-Version: 2.4
Name: blockbuster
Version: 1.5.23
Summary: Utility to detect blocking calls in the async event loop
Project-URL: Repository, https://github.com/cbornet/blockbuster.git
Project-URL: Issues, https://github.com/cbornet/blockbuster/issues
Author-email: Christophe Bornet <bornet.chris@gmail.com>
License-File: LICENSE
Keywords: async,asyncio,block,detect,event loop
Classifier: Development Status :: 3 - Alpha
Classifier: Intended Audience :: Developers
Classifier: License :: OSI Approved :: Apache Software License
Classifier: Programming Language :: Python :: 3.8
Classifier: Programming Language :: Python :: 3.9
Classifier: Programming Language :: Python :: 3.10
Classifier: Programming Language :: Python :: 3.11
Classifier: Programming Language :: Python :: 3.12
Classifier: Programming Language :: Python :: 3.13
Classifier: Topic :: Software Development :: Build Tools
Requires-Python: >=3.8
Requires-Dist: forbiddenfruit>=0.1.4
